Workbook

Sheet 1. Start hier
B2: FinFlowApp — Upload Sjabloon
B3: Vul dit sjabloon in en upload het op finflowapp.ai
B5: IN 4 STAPPEN KLAAR
B6: 2 Tabblad 2 — Dagdata | C6: Vul dagelijks je omzet, kosten en banksaldo in. Dit is het belangrijkste tabblad.
B7: 3 Tabblad 3 — Kostendata | C7: Splits je kosten uit per categorie. Zo zie je in het dashboard waar je geld heen gaat.
B8: 4 Tabblad 4 — Balans | C8: Vul 1x per maand je debiteuren, crediteuren en kaspositie in.
B9: ✓ Upload op finflowapp.ai | C9: Sleep dit bestand in het dashboard. Je cijfers verschijnen direct.
B11: WAT BETEKENEN DE KLEUREN?
B12: Blauwe cellen | C12: Hier vul JIJ gegevens in
B13: Groene cellen | C13: Worden AUTOMATISCH berekend — niet aanpassen
B14: Gele cellen | C14: Belangrijk / verplicht veld
B16: 3 DINGEN OM TE ONTHOUDEN
B17: • Demo data vervangen | C17: Tabblad 2 bevat voorbeelddata (rij 2 t/m 91). Verwijder of overschrijf deze met je eigen cijfers.
B18: • Alleen getallen invullen | C18: Geen €-teken of punten. Schrijf 44200, niet €44.200.
B19: • Datum als DD-MM-JJJJ | C19: Bijvoorbeeld 15-03-2026.
B21: Vragen? Mail naar jenot@finflowapp.ai · finflowapp.ai

Sheet 2. Dagdata
A1: Datum DD-MM-JJJJ | B1: Omzet (€) | C1: Omzet Doel (€, optioneel) | D1: Kosten (€) | E1: Banksaldo (€, einde dag) | F1: Bruto Marge (auto) | G1: Marge % (auto) | H1: Δ Omzet (auto)
A2: 17-02-2026 | B2: 3500 | C2: 4410 | D2: 2417 | E2: 870 | F2: =IF(B2=0,"-",B2-D2) | G2: =IF(B2=0,"-",(B2-D2)/B2) | H2: "-"
A3: 18-02-2026 | B3: 5678 | C3: 4410 | D3: 3512 | E3: 1553 | F3: =IF(B3=0,"-",B3-D3) | G3: =IF(B3=0,"-",(B3-D3)/B3) | H3: =IF(OR(B3=0,B2=0),"-",(B3-B2)/B2)
A4: 19-02-2026 | B4: 4917 | C4: 4410 | D4: 3443 | E4: 1305 | F4: =IF(B4=0,"-",B4-D4) | G4: =IF(B4=0,"-",(B4-D4)/B4) | H4: =IF(OR(B4=0,B3=0),"-",(B4-B3)/B3)
A5: 20-02-2026 | B5: 4761 | C5: 4410 | D5: 3483 | E5: 1125 | F5: =IF(B5=0,"-",B5-D5) | G5: =IF(B5=0,"-",(B5-D5)/B5) | H5: =IF(OR(B5=0,B4=0),"-",(B5-B4)/B4)
A6: 21-02-2026 | B6: 872 | C6: 1260 | D6: 615 | E6: 186 | F6: =IF(B6=0,"-",B6-D6) | G6: =IF(B6=0,"-",(B6-D6)/B6) | H6: =IF(OR(B6=0,B5=0),"-",(B6-B5)/B5)
A7: 22-02-2026 | B7: 775 | C7: 1260 | D7: 480 | E7: 264 | F7: =IF(B7=0,"-",B7-D7) | G7: =IF(B7=0,"-",(B7-D7)/B7) | H7: =IF(OR(B7=0,B6=0),"-",(B7-B6)/B6)
A8: 23-02-2026 | B8: 4472 | C8: 4410 | D8: 3339 | E8: 969 | F8: =IF(B8=0,"-",B8-D8) | G8: =IF(B8=0,"-",(B8-D8)/B8) | H8: =IF(OR(B8=0,B7=0),"-",(B8-B7)/B7)
A9: 24-02-2026 | B9: 5147 | C9: 4410 | D9: 3283 | E9: 1352 | F9: =IF(B9=0,"-",B9-D9) | G9: =IF(B9=0,"-",(B9-D9)/B9) | H9: =IF(OR(B9=0,B8=0),"-",(B9-B8)/B8)
A10: 25-02-2026 | B10: 6031 | C10: 4410 | D10: 4627 | E10: 1252 | F10: =IF(B10=0,"-",B10-D10) | G10: =IF(B10=0,"-",(B10-D10)/B10) | H10: =IF(OR(B10=0,B9=0),"-",(B10-B9)/B9)
A11: 26-02-2026 | B11: 6089 | C11: 4410 | D11: 4216 | E11: 1260 | F11: =IF(B11=0,"-",B11-D11) | G11: =IF(B11=0,"-",(B11-D11)/B11) | H11: =IF(OR(B11=0,B10=0),"-",(B11-B10)/B10)
A12: 27-02-2026 | B12: 4151 | C12: 4410 | D12: 2907 | E12: 918 | F12: =IF(B12=0,"-",B12-D12) | G12: =IF(B12=0,"-",(B12-D12)/B12) | H12: =IF(OR(B12=0,B11=0),"-",(B12-B11)/B11)
A13: 28-02-2026 | B13: 663 | C13: 1260 | D13: 502 | E13: 139 | F13: =IF(B13=0,"-",B13-D13) | G13: =IF(B13=0,"-",(B13-D13)/B13) | H13: =IF(OR(B13=0,B12=0),"-",(B13-B12)/B12)
A14: 01-03-2026 | B14: 748 | C14: 1260 | D14: 452 | E14: 256 | F14: =IF(B14=0,"-",B14-D14) | G14: =IF(B14=0,"-",(B14-D14)/B14) | H14: =IF(OR(B14=0,B13=0),"-",(B14-B13)/B13)
... A91: 17-05-2026 | B91: 666 | C91: 1260 | D91: 517 | E91: 136 | F91: =IF(B91=0,"-",B91-D91) | G91: =IF(B91=0,"-",(B91-D91)/B91) | H91: =IF(OR(B91=0,B90=0),"-",(B91-B90)/B90)
F92: =IF(B92=0,"-",B92-D92) | G92: =IF(B92=0,"-",(B92-D92)/B92) | H92: =IF(OR(B92=0,B91=0),"-",(B92-B91)/B91)
F93: =IF(B93=0,"-",B93-D93) | G93: =IF(B93=0,"-",(B93-D93)/B93) | H93: =IF(OR(B93=0,B92=0),"-",(B93-B92)/B92)
F94: =IF(B94=0,"-",B94-D94) | G94: =IF(B94=0,"-",(B94-D94)/B94) | H94: =IF(OR(B94=0,B93=0),"-",(B94-B93)/B93)
F95: =IF(B95=0,"-",B95-D95) | G95: =IF(B95=0,"-",(B95-D95)/B95) | H95: =IF(OR(B95=0,B94=0),"-",(B95-B94)/B94)
F96: =IF(B96=0,"-",B96-D96) | G96: =IF(B96=0,"-",(B96-D96)/B96) | H96: =IF(OR(B96=0,B95=0),"-",(B96-B95)/B95)
F97: =IF(B97=0,"-",B97-D97) | G97: =IF(B97=0,"-",(B97-D97)/B97) | H97: =IF(OR(B97=0,B96=0),"-",(B97-B96)/B96)
F98: =IF(B98=0,"-",B98-D98) | G98: =IF(B98=0,"-",(B98-D98)/B98) | H98: =IF(OR(B98=0,B97=0),"-",(B98-B97)/B97)
F99: =IF(B99=0,"-",B99-D99) | G99: =IF(B99=0,"-",(B99-D99)/B99) | H99: =IF(OR(B99=0,B98=0),"-",(B99-B98)/B98)
F100: =IF(B100=0,"-",B100-D100) | G100: =IF(B100=0,"-",(B100-D100)/B100) | H100: =IF(OR(B100=0,B99=0),"-",(B100-B99)/B99)
F101: =IF(B101=0,"-",B101-D101) | G101: =IF(B101=0,"-",(B101-D101)/B101) | H101: =IF(OR(B101=0,B100=0),"-",(B101-B100)/B100)
F102: =IF(B102=0,"-",B102-D102) | G102: =IF(B102=0,"-",(B102-D102)/B102) | H102: =IF(OR(B102=0,B101=0),"-",(B102-B101)/B101)
F103: =IF(B103=0,"-",B103-D103) | G103: =IF(B103=0,"-",(B103-D103)/B103) | H103: =IF(OR(B103=0,B102=0),"-",(B103-B102)/B102)
... F456: =IF(B456=0,"-",B456-D456) | G456: =IF(B456=0,"-",(B456-D456)/B456) | H456: =IF(OR(B456=0,B455=0),"-",(B456-B455)/B455)
A457: TOTAAL | B457: =SUM(B2:B456) | C457: =SUM(C2:C456) | D457: =SUM(D2:D456) | E457: =SUM(E2:E456) | F457: =SUM(F2:F456) | G457: =IFERROR(AVERAGE(G2:G456),"-") | H457: "-"

Sheet 3. Kostendata
A1: Kostenpost | B1: Bedrag (€) | C1: Budget (€, optioneel) | D1: % van Totaal (auto) | E1: Toelichting
A2: Personeelskosten | B2: 44200 | C2: 46000 | D2: =IFERROR(B2/SUM($B$2:$B$9),"-") | E2: Salarissen, sociale lasten, pensioen
A3: Inkoopkosten / COGS | B3: 19300 | C3: 20000 | D3: =IFERROR(B3/SUM($B$2:$B$9),"-") | E3: Materiaal, inkoop goederen/diensten
A4: Huisvestingskosten | B4: 8100 | C4: 8000 | D4: =IFERROR(B4/SUM($B$2:$B$9),"-") | E4: Huur, energie, schoonmaak
A5: Marketing & Sales | B5: 4900 | C5: 6000 | D5: =IFERROR(B5/SUM($B$2:$B$9),"-") | E5: Advertenties, events, CRM
A6: ICT & Software | B6: 2800 | C6: 3000 | D6: =IFERROR(B6/SUM($B$2:$B$9),"-") | E6: Licenties, hosting, hardware
A7: Financiële kosten | B7: 1200 | C7: 1500 | D7: =IFERROR(B7/SUM($B$2:$B$9),"-") | E7: Accountant, advies, bank
A8: Afschrijvingen | B8: 1400 | C8: 1400 | D8: =IFERROR(B8/SUM($B$2:$B$9),"-") | E8: Inventaris, machines (maandbedrag)
A9: Overige kosten | B9: 900 | C9: 1000 | D9: =IFERROR(B9/SUM($B$2:$B$9),"-") | E9: Overige operationele kosten
A16: TOTAAL | B16: =SUM(B2:B15) | C16: =SUM(C2:C15) | D16: =1
A18: ℹ Vul de TOTALE kosten per categorie in over dezelfde periode als je Dagdata. Pas de categorienamen gerust aan naar je eigen situatie. Gebruik de lege rijen voor extra kostenposten.

Sheet 4. Balans
A1: Balanspost | B1: Huidig (€) | C1: Vorige periode (€) | D1: Toelichting
A2: VLOTTENDE ACTIVA
A3: Debiteuren (openstaande facturen) | B3: 48500 | C3: 42300 | D3: Openstaande vorderingen op klanten
A4: Kas & Banktegoeden | B4: 32000 | C4: 28500 | D4: Direct beschikbare liquide middelen
A5: Voorraad | B5: 15200 | C5: 17800 | D5: Waarde aanwezige voorraad
A6: Overige vlottende activa | B6: 4800 | C6: 3900 | D6: Vooruitbetaalde kosten e.d.
A7: KORTLOPENDE SCHULDEN
A8: Crediteuren (te betalen facturen) | B8: 22400 | C8: 19800 | D8: Schulden aan leveranciers
A9: Belastingschulden (BTW, LB) | B9: 8200 | C9: 7600 | D9: Nog te betalen belastingen
A10: Overige kortlopende schulden | B10: 3100 | C10: 2800 | D10: Overige schulden < 1 jaar
A11: AANVULLEND
A12: Omzet afgelopen 12 maanden | B12: 1180000 | C12: 1050000 | D12: VERPLICHT — totale jaaromzet, nodig voor DSO
A13: Betalingstermijn klanten (dagen) | B13: 30 | C13: 30 | D13: Afgesproken betaaltermijn met klanten

Sheet 5. Resultaat
B1: Resultaat — Automatische Samenvatting
B2: Berekend uit Dagdata — niet aanpassen
B4: Totaal Omzet | C4: =SUM('2. Dagdata'!B2:B1000) | D4: Totaal Kosten | E4: =SUM('2. Dagdata'!D2:D1000)
B6: Totaal Marge | C6: =SUM('2. Dagdata'!F2:F1000) | D6: Gem. Marge % | E6: =IFERROR(AVERAGE('2. Dagdata'!G2:G1000),0)
B8: Gem. Dagomzet | C8: =IFERROR(AVERAGEIF('2. Dagdata'!B2:B1000,">0"),0) | D8: Totaal Banksaldo | E8: =SUM('2. Dagdata'!E2:E1000)
B10: Budget realisatie | C10: =IFERROR(SUM('2. Dagdata'!B2:B1000)/SUM('2. Dagdata'!C2:C1000),0) | D10: Beste dag omzet | E10: =MAX('2. Dagdata'!B2:B1000)
