Workbook

Sheet 📋 Instructies
B1: FinFlowApp — Dagelijks Upload Sjabloon
B2: Professioneel financieel dashboard voor dagelijkse rapportage · finflowapp.ai
B4: HOE WERKT HET?
B5: Stap 1 — Vul de Dagdata sheet in | C5: Voer dagelijks je omzet, kosten en cashflow in. Blauwe cellen zijn invoervelden.
B6: Stap 2 — Vul Kostendata in (optioneel) | C6: Splits je kosten uit per categorie voor de kostenverdeling in het dashboard.
B7: Stap 3 — Vul Balans in (optioneel) | C7: Voer je debiteuren, crediteuren en kasstand in voor liquiditeitsanalyse.
B8: Stap 4 — Upload naar FinFlowApp | C8: Sleep dit bestand naar het dashboard op finflowapp.ai/dashboard. Alles wordt lokaal verwerkt.
B10: KLEURLEGENDA
B11: 🔵 Blauw | C11: Invoercel — vul hier jouw eigen cijfers in
B12: 🟢 Groen | C12: Automatisch berekend — NIET aanpassen
B13: ⚫ Donker | C13: Label of header — NIET aanpassen
B14: ⚪ Grijs | C14: Toelichting of extra info
B16: DAGDATA — KOLOM UITLEG
B17: Datum ← INVOER | C17: Formaat: DD-MM-YYYY (bijv. 15-05-2026). Weekenden automatisch lager.
B18: Omzet ← INVOER | C18: Totale dagomzet in €. Exclusief BTW. Laat leeg als er geen omzet is.
B19: Budget ← INVOER | C19: Dagelijks omzetdoel in €. Basis voor budget-realisatie berekening.
B20: Kosten ← INVOER | C20: Totale dagkosten in €. Inclusief alle variabele kosten.
B21: Cashflow ← INVOER | C21: Daadwerkelijke kasstroom in €. Niet de winst — maar het kasgeld.
B22: Bruto Marge ← AUTO | C22: Omzet minus Kosten. Automatisch berekend.
B23: Marge % ← AUTO | C23: Bruto marge als percentage van de omzet. Doel: > 30%.
B24: vs Budget ← AUTO | C24: Werkelijke omzet gedeeld door budget. 100% = op target.
B25: Δ Omzet ← AUTO | C25: Procentuele verandering ten opzichte van de vorige dag.
B27: TIPS & VEELGESTELDE VRAGEN
B28: ✓ Dagelijks bijwerken | C28: Voeg elke dag de nieuwe omzet en kosten toe. Het dashboard aggregeert automatisch naar maanden.
B29: ✓ Weekenden leeglaten | C29: Als er geen omzet is op een dag, laat de cel dan leeg. Lege rijen worden overgeslagen.
B30: ✓ Export vanuit je boekhouding | C30: Exporteer dagcijfers uit Exact, Twinfield of Moneybird naar Excel en plak de waarden in kolom B t/m E.
B31: ! Geen formules in blauwe cellen | C31: Vul alleen getallen in — geen €-teken, geen punten als duizendscheiding (bijv. 4200 niet 4.200).
B32: ! Datum altijd als tekst | C32: Datum formaat is DD-MM-YYYY als tekst (bijv. 15-05-2026). Zorg dat Excel het niet als datum herkent.
B33: ✗ Rijen en kolommen NIET verschuiven | C33: Voeg geen rijen in tussen de data. Voeg nieuwe data toe onderaan de bestaande rijen.
B35: FinFlowApp · finflowapp.ai · info@finflowapp.ai · Vragen? Stuur ons een bericht.

Sheet Dagdata
A1: Datum | B1: Omzet | C1: Budget | D1: Kosten | E1: Cashflow | F1: Bruto Marge | G1: Marge % | H1: vs Budget | I1: Δ Omzet
A2: 15-02-2026 | B2: 734 | C2: 1260 | D2: 526 | E2: 165 | F2: =IF(B2=0,"-",B2-D2) | G2: =IF(B2=0,"-",(B2-D2)/B2) | H2: =IF(OR(B2=0,C2=0),"-",B2/C2) | I2: "-"
A3: 16-02-2026 | B3: 3659 | C3: 4410 | D3: 2196 | E3: 1378 | F3: =IF(B3=0,"-",B3-D3) | G3: =IF(B3=0,"-",(B3-D3)/B3) | H3: =IF(OR(B3=0,C3=0),"-",B3/C3) | I3: =IF(OR(B3=0,B2=0),"-",(B3-B2)/B2)
A4: 17-02-2026 | B4: 4825 | C4: 4410 | D4: 2952 | E4: 1443 | F4: =IF(B4=0,"-",B4-D4) | G4: =IF(B4=0,"-",(B4-D4)/B4) | H4: =IF(OR(B4=0,C4=0),"-",B4/C4) | I4: =IF(OR(B4=0,B3=0),"-",(B4-B3)/B3)
A5: 18-02-2026 | B5: 3277 | C5: 4410 | D5: 2419 | E5: 810 | F5: =IF(B5=0,"-",B5-D5) | G5: =IF(B5=0,"-",(B5-D5)/B5) | H5: =IF(OR(B5=0,C5=0),"-",B5/C5) | I5: =IF(OR(B5=0,B4=0),"-",(B5-B4)/B4)
A6: 19-02-2026 | B6: 3442 | C6: 4410 | D6: 2096 | E6: 886 | F6: =IF(B6=0,"-",B6-D6) | G6: =IF(B6=0,"-",(B6-D6)/B6) | H6: =IF(OR(B6=0,C6=0),"-",B6/C6) | I6: =IF(OR(B6=0,B5=0),"-",(B6-B5)/B5)
A7: 20-02-2026 | B7: 4650 | C7: 4410 | D7: 3442 | E7: 856 | F7: =IF(B7=0,"-",B7-D7) | G7: =IF(B7=0,"-",(B7-D7)/B7) | H7: =IF(OR(B7=0,C7=0),"-",B7/C7) | I7: =IF(OR(B7=0,B6=0),"-",(B7-B6)/B6)
A8: 21-02-2026 | B8: 471 | C8: 1260 | D8: 343 | E8: 121 | F8: =IF(B8=0,"-",B8-D8) | G8: =IF(B8=0,"-",(B8-D8)/B8) | H8: =IF(OR(B8=0,C8=0),"-",B8/C8) | I8: =IF(OR(B8=0,B7=0),"-",(B8-B7)/B7)
A9: 22-02-2026 | B9: 1007 | C9: 1260 | D9: 720 | E9: 266 | F9: =IF(B9=0,"-",B9-D9) | G9: =IF(B9=0,"-",(B9-D9)/B9) | H9: =IF(OR(B9=0,C9=0),"-",B9/C9) | I9: =IF(OR(B9=0,B8=0),"-",(B9-B8)/B8)
A10: 23-02-2026 | B10: 4192 | C10: 4410 | D10: 3203 | E10: 820 | F10: =IF(B10=0,"-",B10-D10) | G10: =IF(B10=0,"-",(B10-D10)/B10) | H10: =IF(OR(B10=0,C10=0),"-",B10/C10) | I10: =IF(OR(B10=0,B9=0),"-",(B10-B9)/B9)
A11: 24-02-2026 | B11: 4756 | C11: 4410 | D11: 3032 | E11: 1247 | F11: =IF(B11=0,"-",B11-D11) | G11: =IF(B11=0,"-",(B11-D11)/B11) | H11: =IF(OR(B11=0,C11=0),"-",B11/C11) | I11: =IF(OR(B11=0,B10=0),"-",(B11-B10)/B10)
A12: 25-02-2026 | B12: 3245 | C12: 4410 | D12: 2405 | E12: 685 | F12: =IF(B12=0,"-",B12-D12) | G12: =IF(B12=0,"-",(B12-D12)/B12) | H12: =IF(OR(B12=0,C12=0),"-",B12/C12) | I12: =IF(OR(B12=0,B11=0),"-",(B12-B11)/B11)
A13: 26-02-2026 | B13: 4232 | C13: 4410 | D13: 3292 | E13: 741 | F13: =IF(B13=0,"-",B13-D13) | G13: =IF(B13=0,"-",(B13-D13)/B13) | H13: =IF(OR(B13=0,C13=0),"-",B13/C13) | I13: =IF(OR(B13=0,B12=0),"-",(B13-B12)/B12)
A14: 27-02-2026 | B14: 3967 | C14: 4410 | D14: 2960 | E14: 829 | F14: =IF(B14=0,"-",B14-D14) | G14: =IF(B14=0,"-",(B14-D14)/B14) | H14: =IF(OR(B14=0,C14=0),"-",B14/C14) | I14: =IF(OR(B14=0,B13=0),"-",(B14-B13)/B13)
... A91: 15-05-2026 | B91: 4073 | C91: 4410 | D91: 2970 | E91: 881 | F91: =IF(B91=0,"-",B91-D91) | G91: =IF(B91=0,"-",(B91-D91)/B91) | H91: =IF(OR(B91=0,C91=0),"-",B91/C91) | I91: =IF(OR(B91=0,B90=0),"-",(B91-B90)/B90)
A92: TOTAAL / GEM. | B92: =SUM(B2:B91) | C92: =SUM(C2:C91) | D92: =SUM(D2:D91) | E92: =SUM(E2:E91) | F92: =SUM(F2:F91) | G92: =IFERROR(AVERAGE(G2:G91),"-") | H92: =IFERROR(B92/C92,"-") | I92: "-"
A93: 16-05-2026
A94: 17-05-2026
A95: 18-05-2026
A96: 19-05-2026
A97: 20-05-2026
A98: 21-05-2026
A99: 22-05-2026
A100: 23-05-2026
A101: 24-05-2026
A102: 25-05-2026
A103: 26-05-2026
A104: 27-05-2026
... A122: 14-06-2026

Sheet Samenvatting
B1: FinFlowApp — KPI Samenvatting
B2: Automatisch berekend vanuit Dagdata · Niet aanpassen
B4: Totaal Omzet (90 dgn) | C4: =SUM(Dagdata!B2:B91) | D4: Totaal Kosten (90 dgn) | E4: =SUM(Dagdata!D2:D91)
B6: Totaal Marge (90 dgn) | C6: =SUM(Dagdata!F2:F91) | D6: Gemiddelde marge % | E6: =IFERROR(AVERAGE(Dagdata!G2:G91),0)
B8: Gem. dagomzet | C8: =IFERROR(AVERAGE(Dagdata!B2:B91),0) | D8: Totaal Cashflow | E8: =SUM(Dagdata!E2:E91)
B10: Budget realisatie | C10: =IFERROR(SUM(Dagdata!B2:B91)/SUM(Dagdata!C2:C91),0) | D10: Beste dag omzet | E10: =MAX(Dagdata!B2:B91)

Sheet Kostendata
A1: Categorie | B1: Bedrag (€) | C1: Budget (€) | D1: % Totaal | E1: Toelichting
A2: Personeelskosten | B2: 44200 | C2: 46000 | D2: =IFERROR(B2/SUM($B$2:$B$9),"-") | E2: Salarissen, sociale lasten, pensioen, verzekeringen
A3: Inkoopkosten / COGS | B3: 19300 | C3: 20000 | D3: =IFERROR(B3/SUM($B$2:$B$9),"-") | E3: Materiaal, inkoop goederen/diensten voor verkoop
A4: Huisvestingskosten | B4: 8100 | C4: 8000 | D4: =IFERROR(B4/SUM($B$2:$B$9),"-") | E4: Huur, energie, schoonmaak, beveiliging
A5: Marketing & Sales | B5: 4900 | C5: 6000 | D5: =IFERROR(B5/SUM($B$2:$B$9),"-") | E5: Advertenties, events, CRM, sales tools
A6: ICT & Software | B6: 2800 | C6: 3000 | D6: =IFERROR(B6/SUM($B$2:$B$9),"-") | E6: Licenties, hosting, hardware, support
A7: Financiële kosten | B7: 1200 | C7: 1500 | D7: =IFERROR(B7/SUM($B$2:$B$9),"-") | E7: Accountant, advies, bank, notaris
A8: Afschrijvingen | B8: 1400 | C8: 1400 | D8: =IFERROR(B8/SUM($B$2:$B$9),"-") | E8: Inventaris, machines, immaterieel
A9: Overige kosten | B9: 900 | C9: 1000 | D9: =IFERROR(B9/SUM($B$2:$B$9),"-") | E9: Overige operationele kosten
A16: TOTAAL | B16: =SUM(B2:B15) | C16: =SUM(C2:C15) | D16: =1

Sheet Balans
A1: Balanspost | B1: Huidig (€) | C1: Vorige periode (€) | D1: Toelichting
A2: VLOTTENDE ACTIVA
A3: Debiteuren (openstaande facturen) | B3: 48500 | C3: 42300 | D3: Openstaande vorderingen op klanten
A4: Kas & Banktegoeden | B4: 32000 | C4: 28500 | D4: Direct beschikbare liquide middelen
A5: Voorraad | B5: 15200 | C5: 17800 | D5: Waarde aanwezige voorraad
A6: Overige vlottende activa | B6: 4800 | C6: 3900 | D6: Vooruitbetaalde kosten, nog te ontvangen
A7: KORTLOPENDE SCHULDEN
A8: Crediteuren (te betalen facturen) | B8: 22400 | C8: 19800 | D8: Openstaande schulden aan leveranciers
A9: Belastingschulden (BTW, LB) | B9: 8200 | C9: 7600 | D9: Nog te betalen belastingen
A10: Overige kortlopende schulden | B10: 3100 | C10: 2800 | D10: Overige schulden met looptijd < 1 jaar
A11: AANVULLENDE INFORMATIE
A12: Omzet afgelopen 12 maanden | B12: 1180000 | C12: 1050000 | D12: Voor DSO-berekening in dashboard
A13: Betalingstermijn klanten (dagen) | B13: 30 | C13: 30 | D13: Contractuele betalingstermijn debiteuren
A14: Betalingstermijn leveranciers (dgn) | B14: 45 | C14: 45 | D14: Contractuele betalingstermijn crediteuren
